LICENSE
README.md
setup.py
picmeta/__init__.py
picmeta/cond_meta_env.py
picmeta/hist_meta.py
picmeta/meta_env.py
picmeta/task.py
picmeta/types.py
picmeta.egg-info/PKG-INFO
picmeta.egg-info/SOURCES.txt
picmeta.egg-info/dependency_links.txt
picmeta.egg-info/requires.txt
picmeta.egg-info/top_level.txt